[
  {"category":"Cywilizacje starożytne","question":"Co to jest rewolucja neolityczna?","answers":["Przejście od zbieractwa i koczownictwa do rolnictwa i osiadłego trybu życia","Wynalezienie ognia","Upadek Rzymu","Powstanie pierwszych miast"],"correct_index":0,"explanation":"Rewolucja neolityczna to przejście na uprawę roślin i hodowlę – ludzie przestali wędrować i budowali osady."},
  {"category":"Cywilizacje starożytne","question":"Gdzie powstały najstarsze cywilizacje nad wielkimi rzekami?","answers":["Mezopotamia (Tygrys, Eufrat), Egipt (Nil), Indie (Indus), Chiny (Huanghe)","Tylko w Egipcie","Tylko w Grecji","Tylko w Rzymie"],"correct_index":0,"explanation":"Wielkie rzeki dawały wodę i żyzne gleby – przy nich rozwinęły się pierwsze cywilizacje i pismo."},
  {"category":"Cywilizacje starożytne","question":"Która cywilizacja budowała piramidy i czciła faraonów?","answers":["Starożytny Egipt","Mezopotamia","Grecja","Rzym"],"correct_index":0,"explanation":"W Egipcie faraonowie byli uznawani za bogów; piramidy to grobowce (np. w Gizie)."},
  {"category":"Cywilizacje starożytne","question":"Co to jest politeizm?","answers":["Wiara w wielu bogów (np. w Grecji i Rzymie)","Wiara w jednego Boga","Brak wiary","Wiara w przyrodę"],"correct_index":0,"explanation":"Politeizm to wielobóstwo – Grecy i Rzymianie mieli wielu bogów (Zeus, Jupiter, Atena itd.)."},
  {"category":"Cywilizacje starożytne","question":"Co to jest monoteizm?","answers":["Wiara w jednego Boga (np. judaizm, chrześcijaństwo)","Wiara w wielu bogów","Kult cesarza","Wiara w naturę"],"correct_index":0,"explanation":"Monoteizm to wiara w jednego Boga – religia starożytnego Izraela i chrześcijaństwo."},
  {"category":"Cywilizacje starożytne","question":"Gdzie narodziła się demokracja w formie ustrojowej?","answers":["W starożytnych Atenach (Grecja)","W Rzymie","W Egipcie","W Mezopotamii"],"correct_index":0,"explanation":"W Atenach w V w. p.n.e. obywatele uczestniczyli w zgromadzeniu i głosowaniu – demokracja ateńska."},
  {"category":"Cywilizacje starożytne","question":"Które państwo greckie słynęło z surowego wychowania wojowników?","answers":["Sparta","Ateny","Teby","Kreta"],"correct_index":0,"explanation":"W Sparcie chłopców od dzieciństwa szkolono na żołnierzy; życie podporządkowane było wojsku."},
  {"category":"Cywilizacje starożytne","question":"Co to były igrzyska olimpijskie w starożytności?","answers":["Zawody sportowe w Olimpii (Grecja) na cześć Zeusa – co 4 lata","Tylko biegi","Tylko walki","Tylko w Rzymie"],"correct_index":0,"explanation":"Igrzyska w Olimpii łączyły wszystkie polisy; zwycięzcy byli czczeni; podczas igrzysk obowiązywał rozejm."},
  {"category":"Cywilizacje starożytne","question":"Kto według mitów był królem bogów w Grecji?","answers":["Zeus","Posejdon","Apollo","Hades"],"correct_index":0,"explanation":"Zeus to najwyższy bóg grecki – pan piorunów i nieba; na jego cześć budowano świątynie (np. w Olimpii)."},
  {"category":"Cywilizacje starożytne","question":"Jak nazywało się państwo ze stolicą w Rzymie, które podbiło basen Morza Śródziemnego?","answers":["Starożytny Rzym (republika, potem cesarstwo)","Grecja","Egipt","Kartagina"],"correct_index":0,"explanation":"Rzym najpierw był republiką, potem cesarstwem; podbił Grecję, Egipt, Galię i inne ziemie."},
  {"category":"Cywilizacje starożytne","question":"Co to była republika w Rzymie?","answers":["Ustrój bez króla – władza w ręku senatu i urzędników wybieranych na czas określony","Monarchia","Cesarstwo","Tyrania"],"correct_index":0,"explanation":"W republice rzymskiej konsulowie i senat sprawowali władzę; słowo „res publica” znaczy „rzecz publiczna”."},
  {"category":"Cywilizacje starożytne","question":"Kto był pierwszym cesarzem rzymskim?","answers":["August (Oktawian) – od 27 r. p.n.e.","Juliusz Cezar","Neron","Konstantyn"],"correct_index":0,"explanation":"August zakończył wojny domowe i przyjął tytuł cesarza; od niego zaczyna się okres cesarstwa rzymskiego."},
  {"category":"Cywilizacje starożytne","question":"Gdzie narodziło się chrześcijaństwo?","answers":["W Palestynie (ziemie starożytnego Izraela) – w I w. n.e.","W Rzymie","W Grecji","W Egipcie"],"correct_index":0,"explanation":"Jezus nauczał w Palestynie; chrześcijaństwo rozprzestrzeniło się w cesarstwie rzymskim."},
  {"category":"Cywilizacje starożytne","question":"Który cesarz rzymski zalegalizował chrześcijaństwo?","answers":["Konstantyn Wielki (edykt mediolański 313)","Neron","August","Dioklecjan"],"correct_index":0,"explanation":"Konstantyn w 313 r. dał chrześcijanom swobodę wyznania – koniec prześladowań w cesarstwie."},
  {"category":"Cywilizacje starożytne","question":"Co to jest Mezopotamia?","answers":["Kraina między Tygrysem a Eufratem – kolebka pisma i prawa (Babilon)","Tylko Egipt","Tylko Grecja","Tylko Rzym"],"correct_index":0,"explanation":"W Mezopotamii wynaleziono pismo klinowe i stworzono słynny kodeks Hammurabiego."},
  {"category":"Cywilizacje starożytne","question":"Która religia starożytna jest monoteistyczna i dała początek chrześcijaństwu?","answers":["Religia starożytnego Izraela (judaizm)","Religia egipska","Religia grecka","Religia rzymska"],"correct_index":0,"explanation":"Izraelici wierzyli w jednego Boga (Jahwe); z judaizmu wyrosło chrześcijaństwo."},
  {"category":"Cywilizacje starożytne","question":"Co to był „wiek peryklejski” w Atenach?","answers":["Okres rozkwitu demokracji i kultury w Atenach pod rządami Peryklesa (V w. p.n.e.)","Wiek żelaza","Wiek cesarstwa","Wiek wojen"],"correct_index":0,"explanation":"Perykles wzmocnił demokrację i budował Akropol – złoty wiek Aten."},
  {"category":"Cywilizacje starożytne","question":"Gdzie znajduje się Akropol?","answers":["W Atenach (Grecja) – wzgórze ze świątyniami, m.in. Partenonem","W Rzymie","W Sparcie","W Egipcie"],"correct_index":0,"explanation":"Akropol to wzgórze w Atenach z Partenonem – świątynią Ateny; symbol starożytnej Grecji."},
  {"category":"Cywilizacje starożytne","question":"Która cywilizacja stworzyła prawo „oko za oko”?","answers":["Mezopotamia (kodeks Hammurabiego)","Egipt","Grecja","Rzym"],"correct_index":0,"explanation":"Kodeks Hammurabiego (Babilon) zawierał zasady kar – np. odwet w tej samej mierze."},
  {"category":"Cywilizacje starożytne","question":"Co to jest koloseum w Rzymie?","answers":["Amfiteatr, w którym odbywały się walki gladiatorów i igrzyska","Świątynia","Pałac cesarza","Forum"],"correct_index":0,"explanation":"Koloseum (amfiteatr Flawiuszów) to symbol Rzymu – miejsce igrzysk i walk gladiatorów."},
  {"category":"Cywilizacje starożytne","question":"Które morze łączyło cywilizacje starożytne (Egipt, Grecja, Rzym)?","answers":["Morze Śródziemne","Morze Czarne","Ocean Atlantycki","Morze Czerwone"],"correct_index":0,"explanation":"Basen Morza Śródziemnego był centrum handlu i kultury – „wewnętrzne jezioro” starożytnego świata."},
  {"category":"Cywilizacje starożytne","question":"Co to jest pismo klinowe?","answers":["Pismo wynalezione w Mezopotamii – znaki ryte w glinie (kliny)","Pismo egipskie","Pismo greckie","Pismo łacińskie"],"correct_index":0,"explanation":"Pismo klinowe to jedno z najstarszych pism – używane w Mezopotamii do zapisu na glinianych tabliczkach."},
  {"category":"Cywilizacje starożytne","question":"Kto według tradycji założył Rzym?","answers":["Romulus (legenda: Romulus i Remus, 753 r. p.n.e.)","August","Cezar","Numa Pompiliusz"],"correct_index":0,"explanation":"Legenda mówi, że Romulus założył Rzym w 753 r. p.n.e. – stąd nazwa miasta."},
  {"category":"Cywilizacje starożytne","question":"Co to był senat w Rzymie?","answers":["Rada starszych – najważniejszy organ władzy w republice rzymskiej","Tylko sąd","Tylko wojsko","Tylko świątynia"],"correct_index":0,"explanation":"Senat składał się z byłych urzędników; decydował o polityce i prawie w republice."},
  {"category":"Cywilizacje starożytne","question":"Który filozof grecki uczył na agorze i pytał „wiem, że nic nie wiem”?","answers":["Sokrates","Platon","Arystoteles","Pitagoras"],"correct_index":0,"explanation":"Sokrates nauczał w Atenach przez dialog; skazany na śmierć za „psucie młodzieży” – wypił cykutę."},
  {"category":"Cywilizacje starożytne","question":"Gdzie znajdowała się wyrocznia, do której przybywali Grecy po radę?","answers":["Delfy (wyrocznia Apollina)","Olimpia","Ateny","Sparta"],"correct_index":0,"explanation":"W Delfach kapłanka (Pytia) udzielała odpowiedzi w imieniu boga Apollina – słynna wyrocznia."},
  {"category":"Cywilizacje starożytne","question":"Co to jest „polisa” w starożytnej Grecji?","answers":["Miasto-państwo – niezależna wspólnota z własnym ustrojem (np. Ateny, Sparta)","Tylko miasto","Tylko kolonia","Tylko świątynia"],"correct_index":0,"explanation":"Polis to greckie miasto-państwo – każda miała własne prawa, wojsko i bogów opiekuńczych."},
  {"category":"Cywilizacje starożytne","question":"Kiedy według tradycji odbyły się pierwsze igrzyska olimpijskie?","answers":["776 r. p.n.e. (Grecja)","W czasach Rzymu","W Egipcie","W V w. n.e."],"correct_index":0,"explanation":"Igrzyska w Olimpii datuje się od 776 r. p.n.e. – stąd liczymy olimpiady."},
  {"category":"Cywilizacje starożytne","question":"Która dynastia rządziła Egiptem w czasach budowy piramid?","answers":["Faraonowie (władcy Egiptu) – np. Cheops, Chefren","Cesarze rzymscy","Królowie Babilonu","Basileusowie greccy"],"correct_index":0,"explanation":"Faraon to tytuł władcy Egiptu; piramidy w Gizie wzniesiono w okresie Starego Państwa."},
  {"category":"Cywilizacje starożytne","question":"Co to jest „nasienie chrześcijaństwa” w kontekście Rzymu?","answers":["Rozprzestrzenianie się chrześcijaństwa w cesarstwie mimo prześladowań","Tylko edykt mediolański","Tylko sobory","Tylko mnisi"],"correct_index":0,"explanation":"Chrześcijaństwo rosło w Rzymie i prowincjach; w IV w. stało się religią wspieraną przez cesarza."},
  {"category":"Cywilizacje starożytne","question":"Które państwo starożytne pozostawiło prawo (prawo rzymskie), które wpłynęło na Europę?","answers":["Rzym","Grecja","Egipt","Babilon"],"correct_index":0,"explanation":"Prawo rzymskie (np. kodeks Justyniana) stało się podstawą prawa w wielu krajach Europy."}
]
